numerous/solver/__init__.py
numerous/solver/base.py
numerous/solver/common.py
numerous/solver/events.py
numerous/solver/handlers.py
numerous/solver/interface.py
numerous/solver/models.py
numerous/solver/numerous_solver.py
numerous/solver/solve_states.py
numerous/solver/solver_methods.py
numerous/solver/examples/__init__.py
numerous/solver/examples/models/__init__.py
numerous/solver/examples/models/discrete_events.py
numerous/solver/examples/models/events_with_external_functions.py
numerous/solver/examples/models/model_without_derivatives.py
numerous/solver/examples/models/simple_differential_equation.py
numerous/solver/examples/models/system_of_equations.py
numerous/solver/examples/models/time_events.py
numerous/solver/linalg/__init__.py
numerous/solver/linalg/lapack/__init__.py
numerous/solver/linalg/lapack/lapack_python.py
numerous_solver-3.1.1.dist-info/LICENSE.txt
numerous_solver-3.1.1.dist-info/METADATA
numerous_solver-3.1.1.dist-info/WHEEL
numerous_solver-3.1.1.dist-info/top_level.txt
numerous_solver-3.1.1.dist-info/RECORD
