Metadata-Version: 2.1
Name: numerous-solver
Version: 3.1.1
Summary: Numerous ODE solver
Home-page: 
Author: Tobias Dokkedal Elmoee, EnergyMachines ApS
Author-email: tobias.dokkedal.elmoe@energymachines.com
Classifier: Programming Language :: Python :: 3
Classifier: License :: OSI Approved :: BSD License
Classifier: Operating System :: OS Independent
Requires-Python: >=3.10
License-File: LICENSE.txt
Requires-Dist: numba >=0.56.4
Requires-Dist: scipy >=1.7.1
Requires-Dist: Deprecated >=1.2.13
